setup.py
bin/pepper
bin/pepper-ssh
ff_pepper.egg-info/PKG-INFO
ff_pepper.egg-info/SOURCES.txt
ff_pepper.egg-info/dependency_links.txt
ff_pepper.egg-info/requires.txt
ff_pepper.egg-info/top_level.txt
pepper/__init__.py
pepper/_version.py
pepper/config.py
pepper/connection.py
pepper/gluon.py
pepper/remote_data.py
pepper/simple_logger.py
pepper/frontend/__init__.py
pepper/frontend/cli.py
pepper/frontend/core.py