Metadata-Version: 1.1
Name: ff-pepper
Version: 0.0.3
Summary: Gluon node provision utility
Home-page: https://git.darmstadt.ccc.de/ffda/pepper
Author: Freifunk Darmstadt
Author-email: info@darmstadt.freifunk.net
License: UNKNOWN
Platform: UNKNOWN
Classifier: Topic :: Utilities
Classifier: Development Status :: 3 - Alpha
Classifier: Environment :: Console
Classifier: License :: OSI Approved :: GNU Affero General Public License v3
Classifier: Programming Language :: Python
Classifier: Programming Language :: Python :: 3.3
Classifier: Programming Language :: Python :: 3.4
Classifier: Programming Language :: Python :: 3.5
Classifier: Programming Language :: Python :: 3.6
